{
  "$schema": "https://mintlify.com/docs.json",
  "theme": "mint",
  "name": "Indigenius AI",
  "colors": {
    "primary": "#F79320",
    "light": "#FFEDD5",
    "dark": "#F79320"
  },
  "favicon": "/logo/indigenious-icon.png",
  "navigation": {
    "tabs": [
      {
        "tab": "Guides",
        "groups": [
          {
            "group": "Get Started",
            "pages": [
              "index",
              "quickstart",
              "development"
            ]
          },
          {
            "group": "AgentPro",
            "pages": [
              "AgentPro/welcome",
              "AgentPro/Quickstart",
              "AgentPro/Webcalling",
              "AgentPro/WebCalling"
            ]
          }
        ]
      },
      {
        "tab": "API Reference",
        "groups": [
          {
            "group": "API Documentation",
            "pages": [
              "api-reference/introduction"
            ]
          },
          {
            "group": "Endpoint Examples",
            "pages": [
              "api-reference/endpoint/get",
              "api-reference/endpoint/create",
              "api-reference/endpoint/delete",
              "api-reference/endpoint/webhook"
            ]
          }
        ]
      }
    ],
    "global": {
      "anchors": [
        {
          "anchor": "Documentation",
          "href": "https://cdialai-0073e50a.mintlify.app/",
          "icon": "book-open-cover"
        },
        {
          "anchor": "Community",
          "href": "https://discord.com/channels/1326841048995074129/indigenius.aibycdialcd_99864",
          "icon": "discord"
        },
        {
          "anchor": "Blog",
          "href": "https://indigenius.ai/blog",
          "icon": "newspaper"
        }
      ]
    }
  },
  "logo": {
    "light": "/logo/logo-primary.svg",
    "dark": "/logo/logo-primary-dark.svg"
  },
  "navbar": {
    "links": [
      {
        "label": "Support",
        "href": "mailto:support@indigenius.ai"
      }
    ],
    "primary": {
      "type": "button",
      "label": "Dashboard",
      "href": "https://agent.indigenius.ai"
    }
  },
  "footer": {
    "socials": {
      "website": "https://indigenius.ai/",
      "facebook": "https://m.facebook.com/CdialAI",
      "x-twitter": "https://twitter.com/cdial_ai",
      "youtube": "https://www.youtube.com/@CDIAL_AI",
      "instagram": "https://www.instagram.com/indigenius.ai/"
    }
  }
}